sh3d/AssetManager.py
sh3d/BuildContext.py
sh3d/FileLoader.py
sh3d/__init__.py
sh3d/geometry.py
sh3d/enums/DigestHashEnum.py
sh3d/enums/__init__.py
sh3d/model/BackgroundImage.py
sh3d/model/Baseboard.py
sh3d/model/Color.py
sh3d/model/Compass.py
sh3d/model/Content.py
sh3d/model/ContentDigest.py
sh3d/model/DimensionLine.py
sh3d/model/HasLevel.py
sh3d/model/Home.py
sh3d/model/HomeDoorOrWindow.py
sh3d/model/HomeEnvironment.py
sh3d/model/HomeMaterial.py
sh3d/model/HomePieceOfFurniture.py
sh3d/model/HomeTexture.py
sh3d/model/Label.py
sh3d/model/Level.py
sh3d/model/ModelBase.py
sh3d/model/Polyline.py
sh3d/model/Renderable.py
sh3d/model/Room.py
sh3d/model/Sash.py
sh3d/model/TextStyle.py
sh3d/model/TextureImage.py
sh3d/model/Wall.py
sh3d/model/__init__.py
sh3d/resources/armchair.obj
sh3d/resources/armchair.png
sh3d/resources/bath.obj
sh3d/resources/bath.png
sh3d/resources/bed140x190.obj
sh3d/resources/bed140x190.png
sh3d/resources/bed90x190.obj
sh3d/resources/bed90x190.png
sh3d/resources/bedsideTable.obj
sh3d/resources/bedsideTable.png
sh3d/resources/blueLightSource.png
sh3d/resources/bookcase.obj
sh3d/resources/bookcase.png
sh3d/resources/box.png
sh3d/resources/bunkBed90x190.obj
sh3d/resources/bunkBed90x190.png
sh3d/resources/chair.obj
sh3d/resources/chair.png
sh3d/resources/chest.obj
sh3d/resources/chest.png
sh3d/resources/clothesWasher.obj
sh3d/resources/clothesWasher.png
sh3d/resources/cooker.obj
sh3d/resources/cooker.png
sh3d/resources/cornerBunkBed90x190.obj
sh3d/resources/cornerBunkBed90x190.png
sh3d/resources/cornerSofa.obj
sh3d/resources/cornerSofa.png
sh3d/resources/curveStaircase.obj
sh3d/resources/curveStaircase.png
sh3d/resources/cylinder.png
sh3d/resources/dishwasher.obj
sh3d/resources/dishwasher.png
sh3d/resources/door.obj
sh3d/resources/door.png
sh3d/resources/doorFrame.obj
sh3d/resources/doorFrame.png
sh3d/resources/doubleFrenchWindow126x200.obj
sh3d/resources/doubleFrenchWindow126x200.png
sh3d/resources/doubleHungWindow80x122.obj
sh3d_py-0.2.2.dist-info/licenses/LICENSE
sh3d_py-0.2.2.dist-info/METADATA
sh3d_py-0.2.2.dist-info/WHEEL
sh3d_py-0.2.2.dist-info/top_level.txt
sh3d_py-0.2.2.dist-info/RECORD
