Metadata-Version: 2.4
Name: sh3d.py
Version: 0.2.2
Summary: Sweet home 3D file format implementation in python
Author-email: Adam Schubert <adam.schubert@sg1-game.net>
License-Expression: LGPL-3.0-or-later
Project-URL: Homepage, https://github.com/Salamek/sh3d.py
Classifier: Development Status :: 4 - Beta
Classifier: Intended Audience :: Developers
Classifier: Operating System :: OS Independent
Classifier: Programming Language :: Python
Classifier: Programming Language :: Python :: Implementation :: CPython
Classifier: Programming Language :: Python :: Implementation :: PyPy
Classifier: Programming Language :: Python :: 3.11
Classifier: Programming Language :: Python :: 3.12
Requires-Python: >=3.11
License-File: LICENSE
Requires-Dist: packaging
Requires-Dist: xmltodict
Requires-Dist: javaobj-py3
Requires-Dist: pillow
Requires-Dist: shapely
Provides-Extra: dev
Requires-Dist: tox; extra == "dev"
Dynamic: license-file
